tg_distributions
