Metadata-Version: 1.0
Name: tg-distributions
Version: 0.3
Summary: Gaussian distributions
Home-page: UNKNOWN
Author: Tushar Garg
Author-email: UNKNOWN
License: UNKNOWN
Platform: UNKNOWN
